libwise/__init__.py
libwise/appdirs.py
libwise/colormaps.py
libwise/imgutils.py
libwise/nputils.py
libwise/plotutils.py
libwise/plotutils_base.py
libwise/plotutils_noui.py
libwise/plotutils_ui.py
libwise/presetutils.py
libwise/profileutils.py
libwise/scriptshelper.py
libwise/signalutils.py
libwise/uiutils.py
libwise/waitingspinnerwidget.py
libwise/wavelets.py
libwise/wavelets_coefficients.py
libwise/wtutils.py
libwise/app/PolyRegionEditor.py
libwise/app/Wavelet2DBrowser.py
libwise/app/WaveletBrowser.py
libwise/app/WaveletDenoise.py
libwise/app/WaveletFilterResponse.py
libwise/app/WaveletTransform.py
libwise/app/WaveletTransform2D.py
libwise/app/__init__.py
libwise/app/waveletsui.py
libwise/presets/display.preset
libwise/presets/notebook.preset
libwise/presets/poster_A0.preset
libwise/presets/presentation.preset
libwise/presets/printer_us_letter.preset
libwise/presets/publi_1column.preset
libwise/presets/publi_2columns.preset
libwise/ressource/aa.gif
libwise/ressource/profile.png
libwise/ressource/profile.svg
libwise/ressource/stats.png
libwise/ressource/stats.svg
libwise-0.4.7.data/scripts/fits-crop
libwise-0.4.7.data/scripts/wt-denoise
libwise-0.4.7.data/scripts/wt2d
libwise-0.4.7.dist-info/LICENSE
libwise-0.4.7.dist-info/METADATA
libwise-0.4.7.dist-info/WHEEL
libwise-0.4.7.dist-info/top_level.txt
libwise-0.4.7.dist-info/RECORD
